lpibydevcoder/__init__.py
lpibydevcoder/interpreter.py
lpibydevcoder/lexer.py
lpibydevcoder/parser.py
lpibydevcoder-0.2.0.dist-info/METADATA
lpibydevcoder-0.2.0.dist-info/WHEEL
lpibydevcoder-0.2.0.dist-info/entry_points.txt
lpibydevcoder-0.2.0.dist-info/top_level.txt
lpibydevcoder-0.2.0.dist-info/RECORD
