Metadata-Version: 2.4
Name: lpibydevcoder
Version: 0.2.0
Summary: Гибридный язык программирования: Python + C++ + Rust стиль
Home-page: https://github.com/ZeroMurder/My-Programming-Language
Author: DevCooder
Author-email: zerowanlord@gmail.com
Classifier: Programming Language :: Python :: 3
Classifier: License :: OSI Approved :: MIT License
Classifier: Operating System :: OS Independent
Classifier: Development Status :: 4 - Beta
Classifier: Intended Audience :: Developers
Classifier: Topic :: Software Development :: Interpreters
Requires-Python: >=3.6
Requires-Dist: psutil>=5.9.0
Dynamic: author
Dynamic: author-email
Dynamic: classifier
Dynamic: description
Dynamic: description-content-type
Dynamic: home-page
Dynamic: requires-dist
Dynamic: requires-python
Dynamic: summary
